sportmonks/__init__.py
sportmonks/_base_client.py
sportmonks/_client.py
sportmonks/_compat.py
sportmonks/_constants.py
sportmonks/_exceptions.py
sportmonks/_files.py
sportmonks/_models.py
sportmonks/_qs.py
sportmonks/_resource.py
sportmonks/_response.py
sportmonks/_streaming.py
sportmonks/_types.py
sportmonks/_version.py
sportmonks/pagination.py
sportmonks/py.typed
sportmonks/_utils/__init__.py
sportmonks/_utils/_logs.py
sportmonks/_utils/_proxy.py
sportmonks/_utils/_reflection.py
sportmonks/_utils/_streams.py
sportmonks/_utils/_sync.py
sportmonks/_utils/_transform.py
sportmonks/_utils/_typing.py
sportmonks/_utils/_utils.py
sportmonks/lib/.keep
sportmonks/resources/__init__.py
sportmonks/resources/core/__init__.py
sportmonks/resources/core/continents.py
sportmonks/resources/core/core.py
sportmonks/resources/core/countries.py
sportmonks/resources/core/regions.py
sportmonks/resources/core/timezones.py
sportmonks/resources/core/types.py
sportmonks/resources/football/__init__.py
sportmonks/resources/football/fixtures.py
sportmonks/resources/football/football.py
sportmonks/resources/football/leagues.py
sportmonks/resources/football/livescores.py
sportmonks/resources/football/players.py
sportmonks/resources/football/seasons.py
sportmonks/resources/football/states.py
sportmonks/resources/football/teams.py
sportmonks/resources/football/topscorers.py
sportmonks/resources/football/standings/__init__.py
sportmonks/resources/football/standings/corrections.py
sportmonks/resources/football/standings/live.py
sportmonks/resources/football/standings/standings.py
sportmonks/types/__init__.py
sportmonks/types/core/__init__.py
sportmonks/types/core/continent_list_params.py
sportmonks/types/core/continent_list_response.py
sportmonks/types/core/continent_retrieve_response.py
sportmonks/types/core/country_list_params.py
sportmonks/types/core/country_list_response.py
sportmonks/types/core/country_retrieve_response.py
sportmonks/types/core/country_search_response.py
enotec_sportmonks-2.2.0.dist-info/METADATA
enotec_sportmonks-2.2.0.dist-info/WHEEL
enotec_sportmonks-2.2.0.dist-info/licenses/LICENSE
enotec_sportmonks-2.2.0.dist-info/RECORD
